{"generatedFrom":"public/data/chargers.clean.parquet","generatedThrough":"2026-04-18","state":{"id":"state:bremen","type":"state","name":"Bremen","slug":"bremen","chargingUnits":847,"chargingPoints":1516,"reportedNominalKw":50483.0,"dcFastChargingPoints":360,"dcFastPct":24,"normalChargingPoints":1156,"normalPct":76,"avgKwPerPoint":33,"peakKw":400,"plugSlotsPerUnit":1.8,"powerClass150PlusPct":13,"powerClass50To149Pct":8,"powerClassLowPct":79,"operatorCount":102,"districtCount":2,"cityCount":2,"open247Pct":41,"parking":{"unrestrictedPct":51,"limitedPct":2,"unknownPct":47},"payment":{"appPct":69,"rfidPct":85,"creditCardPct":37,"debitCardPct":32,"plugChargePct":4,"freePct":3},"connectors":{"ccs":true,"type2":true,"tesla":false,"chademo":true,"schuko":false,"cee":false,"mcs":false},"connectorUnitPct":{"ccs":22,"type2":84,"tesla":0,"chademo":2,"schuko":0,"cee":0,"mcs":0},"addedLast12Mo":{"chargingUnits":189,"chargingPoints":277,"reportedNominalKw":15207.0},"firstLiveDate":"2014-04-17","newestDate":"2026-04-14","topOperators":[{"operator":"EWE Go GmbH","chargingUnits":62,"chargingPoints":86,"reportedNominalKw":5818.0,"reportedNominalKwPct":12,"chargingUnitsPct":7,"chargingPointsPct":6},{"operator":"EnBW mobility+ AG und Co.KG","chargingUnits":22,"chargingPoints":47,"reportedNominalKw":4783.0,"reportedNominalKwPct":9,"chargingUnitsPct":3,"chargingPointsPct":3},{"operator":"Mercedes-Benz AG","chargingUnits":101,"chargingPoints":202,"reportedNominalKw":3806.0,"reportedNominalKwPct":8,"chargingUnitsPct":12,"chargingPointsPct":13},{"operator":"Eulektro GmbH","chargingUnits":79,"chargingPoints":179,"reportedNominalKw":3517.0,"reportedNominalKwPct":7,"chargingUnitsPct":9,"chargingPointsPct":12},{"operator":"swb Vertrieb Bremen GmbH","chargingUnits":76,"chargingPoints":149,"reportedNominalKw":3512.0,"reportedNominalKwPct":7,"chargingUnitsPct":9,"chargingPointsPct":10}],"topOperatorReportedNominalKwPct":12,"top5ReportedNominalKwPct":42,"rolloutByYear":[{"year":2014,"addedUnits":1,"cumulativeUnits":1,"cumulativeChargingPoints":2,"cumulativeReportedNominalKw":44.0},{"year":2015,"addedUnits":2,"cumulativeUnits":3,"cumulativeChargingPoints":6,"cumulativeReportedNominalKw":88.0},{"year":2016,"addedUnits":1,"cumulativeUnits":4,"cumulativeChargingPoints":8,"cumulativeReportedNominalKw":132.0},{"year":2017,"addedUnits":21,"cumulativeUnits":25,"cumulativeChargingPoints":49,"cumulativeReportedNominalKw":1083.0},{"year":2018,"addedUnits":19,"cumulativeUnits":44,"cumulativeChargingPoints":91,"cumulativeReportedNominalKw":1953.0},{"year":2019,"addedUnits":59,"cumulativeUnits":103,"cumulativeChargingPoints":211,"cumulativeReportedNominalKw":4726.0},{"year":2020,"addedUnits":29,"cumulativeUnits":132,"cumulativeChargingPoints":274,"cumulativeReportedNominalKw":6363.0},{"year":2021,"addedUnits":27,"cumulativeUnits":159,"cumulativeChargingPoints":325,"cumulativeReportedNominalKw":7261.0},{"year":2022,"addedUnits":114,"cumulativeUnits":273,"cumulativeChargingPoints":564,"cumulativeReportedNominalKw":14161.0},{"year":2023,"addedUnits":97,"cumulativeUnits":370,"cumulativeChargingPoints":741,"cumulativeReportedNominalKw":20122.0},{"year":2024,"addedUnits":256,"cumulativeUnits":626,"cumulativeChargingPoints":1175,"cumulativeReportedNominalKw":32896.0},{"year":2025,"addedUnits":201,"cumulativeUnits":827,"cumulativeChargingPoints":1483,"cumulativeReportedNominalKw":48777.0},{"year":2026,"addedUnits":20,"cumulativeUnits":847,"cumulativeChargingPoints":1516,"cumulativeReportedNominalKw":50483.0}],"districtsFile":"data/regions/districts/by-state/bremen.json","rank":16,"topDistricts":[{"id":"district:bremen/kreisfreie-stadt-bremen","name":"Kreisfreie Stadt Bremen","slug":"kreisfreie-stadt-bremen","rank":1,"chargingUnits":761,"chargingPoints":1344,"reportedNominalKw":43383.0,"dcFastPct":21,"operatorCount":91},{"id":"district:bremen/kreisfreie-stadt-bremerhaven","name":"Kreisfreie Stadt Bremerhaven","slug":"kreisfreie-stadt-bremerhaven","rank":2,"chargingUnits":86,"chargingPoints":172,"reportedNominalKw":7100.0,"dcFastPct":44,"operatorCount":29}],"topCities":[{"id":"city:bremen/kreisfreie-stadt-bremen/bremen","name":"Bremen","slug":"bremen","rank":1,"chargingUnits":761,"chargingPoints":1344,"reportedNominalKw":43383.0,"dcFastPct":21,"operatorCount":91},{"id":"city:bremen/kreisfreie-stadt-bremerhaven/bremerhaven","name":"Bremerhaven","slug":"bremerhaven","rank":2,"chargingUnits":86,"chargingPoints":172,"reportedNominalKw":7100.0,"dcFastPct":44,"operatorCount":29}]},"districts":[{"id":"district:bremen/kreisfreie-stadt-bremen","type":"district","name":"Kreisfreie Stadt Bremen","slug":"kreisfreie-stadt-bremen","chargingUnits":761,"chargingPoints":1344,"reportedNominalKw":43383.0,"dcFastChargingPoints":284,"dcFastPct":21,"normalChargingPoints":1060,"normalPct":79,"avgKwPerPoint":32,"peakKw":400,"plugSlotsPerUnit":1.8,"powerClass150PlusPct":12,"powerClass50To149Pct":7,"powerClassLowPct":81,"operatorCount":91,"districtCount":1,"cityCount":1,"open247Pct":42,"parking":{"unrestrictedPct":51,"limitedPct":1,"unknownPct":48},"payment":{"appPct":68,"rfidPct":86,"creditCardPct":37,"debitCardPct":32,"plugChargePct":5,"freePct":3},"connectors":{"ccs":true,"type2":true,"tesla":false,"chademo":true,"schuko":false,"cee":false,"mcs":false},"connectorUnitPct":{"ccs":19,"type2":86,"tesla":0,"chademo":2,"schuko":0,"cee":0,"mcs":0},"addedLast12Mo":{"chargingUnits":167,"chargingPoints":235,"reportedNominalKw":11980.0},"firstLiveDate":"2014-04-17","newestDate":"2026-04-14","parent":{"state":"Bremen","stateSlug":"bremen"},"topOperators":[{"operator":"EWE Go GmbH","chargingUnits":55,"chargingPoints":72,"reportedNominalKw":5280.0,"reportedNominalKwPct":12,"chargingUnitsPct":7,"chargingPointsPct":5},{"operator":"EnBW mobility+ AG und Co.KG","chargingUnits":17,"chargingPoints":35,"reportedNominalKw":3845.0,"reportedNominalKwPct":9,"chargingUnitsPct":2,"chargingPointsPct":3},{"operator":"Mercedes-Benz AG","chargingUnits":101,"chargingPoints":202,"reportedNominalKw":3806.0,"reportedNominalKwPct":9,"chargingUnitsPct":13,"chargingPointsPct":15},{"operator":"Eulektro GmbH","chargingUnits":79,"chargingPoints":179,"reportedNominalKw":3517.0,"reportedNominalKwPct":8,"chargingUnitsPct":10,"chargingPointsPct":13},{"operator":"swb Vertrieb Bremen GmbH","chargingUnits":59,"chargingPoints":116,"reportedNominalKw":2780.0,"reportedNominalKwPct":6,"chargingUnitsPct":8,"chargingPointsPct":9}],"topOperatorReportedNominalKwPct":12,"top5ReportedNominalKwPct":44,"rolloutByYear":[{"year":2014,"addedUnits":1,"cumulativeUnits":1,"cumulativeChargingPoints":2,"cumulativeReportedNominalKw":44.0},{"year":2017,"addedUnits":14,"cumulativeUnits":15,"cumulativeChargingPoints":30,"cumulativeReportedNominalKw":709.0},{"year":2018,"addedUnits":13,"cumulativeUnits":28,"cumulativeChargingPoints":58,"cumulativeReportedNominalKw":1271.0},{"year":2019,"addedUnits":56,"cumulativeUnits":84,"cumulativeChargingPoints":172,"cumulativeReportedNominalKw":3912.0},{"year":2020,"addedUnits":28,"cumulativeUnits":112,"cumulativeChargingPoints":233,"cumulativeReportedNominalKw":5527.0},{"year":2021,"addedUnits":22,"cumulativeUnits":134,"cumulativeChargingPoints":274,"cumulativeReportedNominalKw":6260.0},{"year":2022,"addedUnits":108,"cumulativeUnits":242,"cumulativeChargingPoints":501,"cumulativeReportedNominalKw":12772.0},{"year":2023,"addedUnits":85,"cumulativeUnits":327,"cumulativeChargingPoints":655,"cumulativeReportedNominalKw":17095.0},{"year":2024,"addedUnits":241,"cumulativeUnits":568,"cumulativeChargingPoints":1054,"cumulativeReportedNominalKw":29232.0},{"year":2025,"addedUnits":175,"cumulativeUnits":743,"cumulativeChargingPoints":1315,"cumulativeReportedNominalKw":41797.0},{"year":2026,"addedUnits":18,"cumulativeUnits":761,"cumulativeChargingPoints":1344,"cumulativeReportedNominalKw":43383.0}],"citiesFile":"data/regions/cities/by-district/bremen/kreisfreie-stadt-bremen.json","rank":1,"topCities":[{"id":"city:bremen/kreisfreie-stadt-bremen/bremen","name":"Bremen","slug":"bremen","rank":1,"chargingUnits":761,"chargingPoints":1344,"reportedNominalKw":43383.0,"dcFastPct":21,"operatorCount":91}]},{"id":"district:bremen/kreisfreie-stadt-bremerhaven","type":"district","name":"Kreisfreie Stadt Bremerhaven","slug":"kreisfreie-stadt-bremerhaven","chargingUnits":86,"chargingPoints":172,"reportedNominalKw":7100.0,"dcFastChargingPoints":76,"dcFastPct":44,"normalChargingPoints":96,"normalPct":56,"avgKwPerPoint":41,"peakKw":300,"plugSlotsPerUnit":2.0,"powerClass150PlusPct":22,"powerClass50To149Pct":21,"powerClassLowPct":57,"operatorCount":29,"districtCount":1,"cityCount":1,"open247Pct":31,"parking":{"unrestrictedPct":55,"limitedPct":7,"unknownPct":38},"payment":{"appPct":73,"rfidPct":72,"creditCardPct":35,"debitCardPct":29,"plugChargePct":2,"freePct":2},"connectors":{"ccs":true,"type2":true,"tesla":false,"chademo":false,"schuko":false,"cee":false,"mcs":false},"connectorUnitPct":{"ccs":44,"type2":67,"tesla":0,"chademo":0,"schuko":0,"cee":0,"mcs":0},"addedLast12Mo":{"chargingUnits":22,"chargingPoints":42,"reportedNominalKw":3227.0},"firstLiveDate":"2015-04-09","newestDate":"2026-03-19","parent":{"state":"Bremen","stateSlug":"bremen"},"topOperators":[{"operator":"BP Europa SE","chargingUnits":4,"chargingPoints":8,"reportedNominalKw":1200.0,"reportedNominalKwPct":17,"chargingUnitsPct":5,"chargingPointsPct":5},{"operator":"EnBW mobility+ AG und Co.KG","chargingUnits":5,"chargingPoints":12,"reportedNominalKw":938.0,"reportedNominalKwPct":13,"chargingUnitsPct":6,"chargingPointsPct":7},{"operator":"swb Vertrieb Bremen GmbH","chargingUnits":17,"chargingPoints":33,"reportedNominalKw":732.0,"reportedNominalKwPct":10,"chargingUnitsPct":20,"chargingPointsPct":19},{"operator":"Pfalzwerke AG","chargingUnits":3,"chargingPoints":6,"reportedNominalKw":650.0,"reportedNominalKwPct":9,"chargingUnitsPct":3,"chargingPointsPct":3},{"operator":"E.ON Drive Infrastructure GmbH","chargingUnits":3,"chargingPoints":6,"reportedNominalKw":600.0,"reportedNominalKwPct":8,"chargingUnitsPct":3,"chargingPointsPct":3}],"topOperatorReportedNominalKwPct":17,"top5ReportedNominalKwPct":58,"rolloutByYear":[{"year":2015,"addedUnits":2,"cumulativeUnits":2,"cumulativeChargingPoints":4,"cumulativeReportedNominalKw":44.0},{"year":2016,"addedUnits":1,"cumulativeUnits":3,"cumulativeChargingPoints":6,"cumulativeReportedNominalKw":88.0},{"year":2017,"addedUnits":7,"cumulativeUnits":10,"cumulativeChargingPoints":19,"cumulativeReportedNominalKw":374.0},{"year":2018,"addedUnits":6,"cumulativeUnits":16,"cumulativeChargingPoints":33,"cumulativeReportedNominalKw":682.0},{"year":2019,"addedUnits":3,"cumulativeUnits":19,"cumulativeChargingPoints":39,"cumulativeReportedNominalKw":814.0},{"year":2020,"addedUnits":1,"cumulativeUnits":20,"cumulativeChargingPoints":41,"cumulativeReportedNominalKw":836.0},{"year":2021,"addedUnits":5,"cumulativeUnits":25,"cumulativeChargingPoints":51,"cumulativeReportedNominalKw":1001.0},{"year":2022,"addedUnits":6,"cumulativeUnits":31,"cumulativeChargingPoints":63,"cumulativeReportedNominalKw":1389.0},{"year":2023,"addedUnits":12,"cumulativeUnits":43,"cumulativeChargingPoints":86,"cumulativeReportedNominalKw":3027.0},{"year":2024,"addedUnits":15,"cumulativeUnits":58,"cumulativeChargingPoints":121,"cumulativeReportedNominalKw":3664.0},{"year":2025,"addedUnits":26,"cumulativeUnits":84,"cumulativeChargingPoints":168,"cumulativeReportedNominalKw":6980.0},{"year":2026,"addedUnits":2,"cumulativeUnits":86,"cumulativeChargingPoints":172,"cumulativeReportedNominalKw":7100.0}],"citiesFile":"data/regions/cities/by-district/bremen/kreisfreie-stadt-bremerhaven.json","rank":2,"topCities":[{"id":"city:bremen/kreisfreie-stadt-bremerhaven/bremerhaven","name":"Bremerhaven","slug":"bremerhaven","rank":1,"chargingUnits":86,"chargingPoints":172,"reportedNominalKw":7100.0,"dcFastPct":44,"operatorCount":29}]}]}