{"generatedFrom":"public/data/chargers.clean.parquet","generatedThrough":"2026-04-18","district":{"id":"district:schleswig-holstein/kreisfreie-stadt-neumunster","type":"district","name":"Kreisfreie Stadt Neumünster","slug":"kreisfreie-stadt-neumunster","chargingUnits":169,"chargingPoints":288,"reportedNominalKw":14943.0,"dcFastChargingPoints":85,"dcFastPct":30,"normalChargingPoints":203,"normalPct":70,"avgKwPerPoint":52,"peakKw":400,"plugSlotsPerUnit":1.7,"powerClass150PlusPct":23,"powerClass50To149Pct":1,"powerClassLowPct":76,"operatorCount":29,"districtCount":1,"cityCount":1,"open247Pct":15,"parking":{"unrestrictedPct":21,"limitedPct":1,"unknownPct":78},"payment":{"appPct":92,"rfidPct":73,"creditCardPct":14,"debitCardPct":11,"plugChargePct":2,"freePct":12},"connectors":{"ccs":true,"type2":true,"tesla":false,"chademo":true,"schuko":false,"cee":false,"mcs":false},"connectorUnitPct":{"ccs":33,"type2":69,"tesla":0,"chademo":4,"schuko":0,"cee":0,"mcs":0},"addedLast12Mo":{"chargingUnits":10,"chargingPoints":20,"reportedNominalKw":1212.0},"firstLiveDate":"2016-04-01","newestDate":"2026-01-01","parent":{"state":"Schleswig-Holstein","stateSlug":"schleswig-holstein"},"topOperators":[{"operator":"Tesla Germany GmbH","chargingUnits":20,"chargingPoints":20,"reportedNominalKw":5000.0,"reportedNominalKwPct":33,"chargingUnitsPct":12,"chargingPointsPct":7},{"operator":"SWN Stadtwerke Neumünster GmbH","chargingUnits":68,"chargingPoints":135,"reportedNominalKw":2785.0,"reportedNominalKwPct":19,"chargingUnitsPct":40,"chargingPointsPct":47},{"operator":"IONITY GmbH","chargingUnits":6,"chargingPoints":6,"reportedNominalKw":2100.0,"reportedNominalKwPct":14,"chargingUnitsPct":4,"chargingPointsPct":2},{"operator":"EnBW mobility+ AG und Co.KG","chargingUnits":5,"chargingPoints":11,"reportedNominalKw":950.0,"reportedNominalKwPct":6,"chargingUnitsPct":3,"chargingPointsPct":4},{"operator":"Herbert Voigt GmbH & Co. KG","chargingUnits":2,"chargingPoints":4,"reportedNominalKw":800.0,"reportedNominalKwPct":5,"chargingUnitsPct":1,"chargingPointsPct":1}],"topOperatorReportedNominalKwPct":33,"top5ReportedNominalKwPct":78,"rolloutByYear":[{"year":2016,"addedUnits":5,"cumulativeUnits":5,"cumulativeChargingPoints":9,"cumulativeReportedNominalKw":198.0},{"year":2017,"addedUnits":4,"cumulativeUnits":9,"cumulativeChargingPoints":17,"cumulativeReportedNominalKw":472.0},{"year":2018,"addedUnits":1,"cumulativeUnits":10,"cumulativeChargingPoints":19,"cumulativeReportedNominalKw":516.0},{"year":2019,"addedUnits":6,"cumulativeUnits":16,"cumulativeChargingPoints":27,"cumulativeReportedNominalKw":2053.0},{"year":2020,"addedUnits":2,"cumulativeUnits":18,"cumulativeChargingPoints":29,"cumulativeReportedNominalKw":2403.0},{"year":2022,"addedUnits":43,"cumulativeUnits":61,"cumulativeChargingPoints":115,"cumulativeReportedNominalKw":3916.0},{"year":2023,"addedUnits":75,"cumulativeUnits":136,"cumulativeChargingPoints":226,"cumulativeReportedNominalKw":11129.0},{"year":2024,"addedUnits":16,"cumulativeUnits":152,"cumulativeChargingPoints":256,"cumulativeReportedNominalKw":12181.0},{"year":2025,"addedUnits":15,"cumulativeUnits":167,"cumulativeChargingPoints":284,"cumulativeReportedNominalKw":14143.0},{"year":2026,"addedUnits":2,"cumulativeUnits":169,"cumulativeChargingPoints":288,"cumulativeReportedNominalKw":14943.0}],"citiesFile":"data/regions/cities/by-district/schleswig-holstein/kreisfreie-stadt-neumunster.json","rank":10,"topCities":[{"id":"city:schleswig-holstein/kreisfreie-stadt-neumunster/neumunster","name":"Neumünster","slug":"neumunster","rank":1,"chargingUnits":169,"chargingPoints":288,"reportedNominalKw":14943.0,"dcFastPct":30,"operatorCount":29}]},"cities":[{"id":"city:schleswig-holstein/kreisfreie-stadt-neumunster/neumunster","type":"city","name":"Neumünster","slug":"neumunster","chargingUnits":169,"chargingPoints":288,"reportedNominalKw":14943.0,"dcFastChargingPoints":85,"dcFastPct":30,"normalChargingPoints":203,"normalPct":70,"avgKwPerPoint":52,"peakKw":400,"plugSlotsPerUnit":1.7,"powerClass150PlusPct":23,"powerClass50To149Pct":1,"powerClassLowPct":76,"operatorCount":29,"districtCount":1,"cityCount":1,"open247Pct":15,"parking":{"unrestrictedPct":21,"limitedPct":1,"unknownPct":78},"payment":{"appPct":92,"rfidPct":73,"creditCardPct":14,"debitCardPct":11,"plugChargePct":2,"freePct":12},"connectors":{"ccs":true,"type2":true,"tesla":false,"chademo":true,"schuko":false,"cee":false,"mcs":false},"connectorUnitPct":{"ccs":33,"type2":69,"tesla":0,"chademo":4,"schuko":0,"cee":0,"mcs":0},"addedLast12Mo":{"chargingUnits":10,"chargingPoints":20,"reportedNominalKw":1212.0},"firstLiveDate":"2016-04-01","newestDate":"2026-01-01","parent":{"state":"Schleswig-Holstein","stateSlug":"schleswig-holstein","district":"Kreisfreie Stadt Neumünster","districtSlug":"kreisfreie-stadt-neumunster"},"topOperators":[{"operator":"Tesla Germany GmbH","chargingUnits":20,"chargingPoints":20,"reportedNominalKw":5000.0,"reportedNominalKwPct":33,"chargingUnitsPct":12,"chargingPointsPct":7},{"operator":"SWN Stadtwerke Neumünster GmbH","chargingUnits":68,"chargingPoints":135,"reportedNominalKw":2785.0,"reportedNominalKwPct":19,"chargingUnitsPct":40,"chargingPointsPct":47},{"operator":"IONITY GmbH","chargingUnits":6,"chargingPoints":6,"reportedNominalKw":2100.0,"reportedNominalKwPct":14,"chargingUnitsPct":4,"chargingPointsPct":2},{"operator":"EnBW mobility+ AG und Co.KG","chargingUnits":5,"chargingPoints":11,"reportedNominalKw":950.0,"reportedNominalKwPct":6,"chargingUnitsPct":3,"chargingPointsPct":4},{"operator":"Herbert Voigt GmbH & Co. KG","chargingUnits":2,"chargingPoints":4,"reportedNominalKw":800.0,"reportedNominalKwPct":5,"chargingUnitsPct":1,"chargingPointsPct":1}],"topOperatorReportedNominalKwPct":33,"top5ReportedNominalKwPct":78,"rolloutByYear":[{"year":2016,"addedUnits":5,"cumulativeUnits":5,"cumulativeChargingPoints":9,"cumulativeReportedNominalKw":198.0},{"year":2017,"addedUnits":4,"cumulativeUnits":9,"cumulativeChargingPoints":17,"cumulativeReportedNominalKw":472.0},{"year":2018,"addedUnits":1,"cumulativeUnits":10,"cumulativeChargingPoints":19,"cumulativeReportedNominalKw":516.0},{"year":2019,"addedUnits":6,"cumulativeUnits":16,"cumulativeChargingPoints":27,"cumulativeReportedNominalKw":2053.0},{"year":2020,"addedUnits":2,"cumulativeUnits":18,"cumulativeChargingPoints":29,"cumulativeReportedNominalKw":2403.0},{"year":2022,"addedUnits":43,"cumulativeUnits":61,"cumulativeChargingPoints":115,"cumulativeReportedNominalKw":3916.0},{"year":2023,"addedUnits":75,"cumulativeUnits":136,"cumulativeChargingPoints":226,"cumulativeReportedNominalKw":11129.0},{"year":2024,"addedUnits":16,"cumulativeUnits":152,"cumulativeChargingPoints":256,"cumulativeReportedNominalKw":12181.0},{"year":2025,"addedUnits":15,"cumulativeUnits":167,"cumulativeChargingPoints":284,"cumulativeReportedNominalKw":14143.0},{"year":2026,"addedUnits":2,"cumulativeUnits":169,"cumulativeChargingPoints":288,"cumulativeReportedNominalKw":14943.0}],"rank":1}]}